setup.py
pyharbor.egg-info/PKG-INFO
pyharbor.egg-info/SOURCES.txt
pyharbor.egg-info/dependency_links.txt
pyharbor.egg-info/top_level.txt
pyharborclient/__init__.py
pyharborclient/harborclient.py
pyharborclient/test_harborclient.py
pyharborclient/examples/__init__.py
pyharborclient/examples/change_password.py
pyharborclient/examples/check_project_exist.py
pyharborclient/examples/create_project.py
pyharborclient/examples/create_user.py
pyharborclient/examples/delete_repository.py
pyharborclient/examples/delete_user.py
pyharborclient/examples/get_logs.py
pyharborclient/examples/get_project_id_from_name.py
pyharborclient/examples/get_projects.py
pyharborclient/examples/get_repositories.py
pyharborclient/examples/get_repository_manifests.py
pyharborclient/examples/get_repository_tags.py
pyharborclient/examples/get_statistics.py
pyharborclient/examples/get_top_accessed_repositories.py
pyharborclient/examples/get_users.py
pyharborclient/examples/promote_as_admin.py
pyharborclient/examples/search.py
pyharborclient/examples/set_project_publicity.py
pyharborclient/examples/test_harborclient.py
pyharborclient/examples/update_user_profile.py