Metadata-Version: 1.0
Name: pyharbor
Version: 1.2.7
Summary: The harbor python SDK
Home-page: https://github.com/zhangliu520/python-harbor.git
Author: mrzl
Author-email: 752477168@qq.com
License: MIT Licence
Keywords: pyharbor,harbor,python
Platform: any
